{"web":{"client_id":"456816466000-fllno6mknd0nq7fivp486gkd7f35g00f.apps.googleusercontent.com","project_id":"theorchid","auth_uri":"https://accounts.google.com/o/oauth2/auth","token_uri":"https://oauth2.googleapis.com/token","auth_provider_x509_cert_url":"https://www.googleapis.com/oauth2/v1/certs","client_secret":"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","redirect_uris":["https://theorchid.azurewebsites.net/.auth/login/google/callback","https://127.0.0.1:8000/.auth/login/google/callback"],"javascript_origins":["http://127.0.0.1:8000","https://theorchid.azurewebsites.net"]}}